wolfcode/.gitignore
wolfcode/.secrets_template.toml
wolfcode/__init__.py
wolfcode/agents/CodeAuditAgent.py
wolfcode/agents/CodingStandardsChecker.py
wolfcode/agents/__init__.py
wolfcode/cli.py
wolfcode/config.py
wolfcode/definitions.py
wolfcode/output_schemas/AuditReport.py
wolfcode/output_schemas/CodingStandardsReview.py
wolfcode/output_schemas/__init__.py
wolfcode/settings/check_coding_standards_config.toml
wolfcode/settings/code_audit_config.toml
wolfcode/settings/wolfssl_coding_standards.toml
wolfcode/utils/__init__.py
wolfcode/utils/read_text.py
wolfcode-0.1.0.dist-info/METADATA
wolfcode-0.1.0.dist-info/WHEEL
wolfcode-0.1.0.dist-info/entry_points.txt
wolfcode-0.1.0.dist-info/RECORD
