Metadata-Version: 2.1
Name: wolfcode
Version: 0.1.0
Summary: 
Author: Shingo Morimoto
Author-email: shingo@wolfssl.com
Requires-Python: >=3.11,<4.0
Classifier: Programming Language :: Python :: 3
Classifier: Programming Language :: Python :: 3.11
Classifier: Programming Language :: Python :: 3.12
Requires-Dist: dynaconf (>=3.2.4,<4.0.0)
Requires-Dist: gitpython (>=3.1.42,<4.0.0)
Requires-Dist: langchain (>=0.1.11,<0.2.0)
Requires-Dist: langchain-community (>=0.0.27,<0.0.28)
Requires-Dist: langchain-openai (>=0.0.8,<0.0.9)
Requires-Dist: openai (>=1.13.3,<2.0.0)
Requires-Dist: rich (>=13.7.1,<14.0.0)
Requires-Dist: typer (>=0.9.0,<0.10.0)
